coinbase_agentkit_pydantic_ai/__init__.py
coinbase_agentkit_pydantic_ai/pydantic_ai_tools.py
coinbase_agentkit_pydantic_ai-0.1.0.dist-info/METADATA
coinbase_agentkit_pydantic_ai-0.1.0.dist-info/WHEEL
coinbase_agentkit_pydantic_ai-0.1.0.dist-info/RECORD
