Metadata-Version: 2.4
Name: coinbase-agentkit-pydantic-ai
Version: 0.1.0
Summary: Coinbase AgentKit PydanticAI extension
Author-email: Logan Kang <kcs93023@gmail.com>
License-Expression: Apache-2.0
Keywords: agent,ai,cdp,coinbase,crypto,pydantic-ai,sdk
Requires-Python: ~=3.10
Requires-Dist: coinbase-agentkit<0.8,>=0.7.2
Requires-Dist: nest-asyncio<2,>=1.6.0
Requires-Dist: pydantic-ai<0.5,>=0.4.0
Requires-Dist: pytest-asyncio<0.26,>=0.25.3
Requires-Dist: python-dotenv<2,>=1.0.1
Requires-Dist: setuptools<70,>=69.0.3
